zpystream/__init__.py
zpystream/stream.py
zpystream/util.py
zpystream-0.1.1.dist-info/LICENSE.txt
zpystream-0.1.1.dist-info/METADATA
zpystream-0.1.1.dist-info/WHEEL
zpystream-0.1.1.dist-info/top_level.txt
zpystream-0.1.1.dist-info/RECORD
