Metadata-Version: 2.1
Name: zpystream
Version: 0.1.1
Summary: zpystream
Home-page: UNKNOWN
Author: zgl
Author-email: 
License: MIT
Keywords: zpystream
Platform: UNKNOWN
License-File: LICENSE.txt
